audio_metrics/__init__.py
audio_metrics/audio_metrics.py
audio_metrics/data.py
audio_metrics/embed.py
audio_metrics/example_utils.py
audio_metrics/mix_functions.py
audio_metrics/projection.py
audio_metrics/embedders/__init__.py
audio_metrics/embedders/clap.py
audio_metrics/embedders/vggish.py
audio_metrics/metrics/apa.py
audio_metrics/metrics/fad.py
audio_metrics/metrics/kd.py
audio_metrics/metrics/prdc.py
audio_metrics/tests/test_audio_metrics.py
audio_metrics/tests/test_data.py
audio_metrics/util/audio.py
audio_metrics/util/cpu_parallel.py
audio_metrics/util/get_url.py
audio_metrics/util/gpu_parallel.py
audio_metrics/util/shuffle.py
audio_metrics-1.0.4.dist-info/METADATA
audio_metrics-1.0.4.dist-info/WHEEL
audio_metrics-1.0.4.dist-info/licenses/LICENSE
audio_metrics-1.0.4.dist-info/RECORD
