Metadata-Version: 2.4
Name: audio-metrics
Version: 1.0.4
Summary: Metrics to measure the quality of audio
Author: Maarten Grachten
License-File: LICENSE
Requires-Python: >=3.10
Requires-Dist: appdirs
Requires-Dist: einops
Requires-Dist: laion-clap>=1.1.6
Requires-Dist: numba
Requires-Dist: numpy-audio-limiter
Requires-Dist: opt-einsum
Requires-Dist: prdc
Requires-Dist: pyloudnorm
Requires-Dist: scikit-learn
Requires-Dist: soxr
Requires-Dist: torch
Requires-Dist: torchvision; python_version < '3.13'
Requires-Dist: torchvision>=0.24; python_version >= '3.13'
Requires-Dist: tqdm
Provides-Extra: dev
Requires-Dist: flake8; extra == 'dev'
Requires-Dist: ipdb; extra == 'dev'
Requires-Dist: ipython; extra == 'dev'
Requires-Dist: pylint; extra == 'dev'
Requires-Dist: pytest; extra == 'dev'
Requires-Dist: python-lsp-ruff; extra == 'dev'
Requires-Dist: python-lsp-server; extra == 'dev'
Requires-Dist: rich; extra == 'dev'
Requires-Dist: ruff; extra == 'dev'
Provides-Extra: examples
Requires-Dist: musdb; extra == 'examples'
Requires-Dist: setuptools; extra == 'examples'
Requires-Dist: soundfile; extra == 'examples'
